genai4seqcls/__init__.py
genai4seqcls/balancing_methods.py
genai4seqcls/callbacks.py
genai4seqcls/losses.py
genai4seqcls/metrics.py
genai4seqcls/models.py
genai4seqcls/preproc.py
genai4seqcls/visualizations.py
genai4seqcls-1.0.5.dist-info/licenses/LICENSE
genai4seqcls-1.0.5.dist-info/METADATA
genai4seqcls-1.0.5.dist-info/WHEEL
genai4seqcls-1.0.5.dist-info/top_level.txt
genai4seqcls-1.0.5.dist-info/RECORD
